papermcpy/__init__.py
papermcpy/classes.py
papermcpy/download.py
papermcpy/projects.py
papermcpy/utils.py
papermcpy/versions.py
papermcpy/a/__init__.py
papermcpy/a/download.py
papermcpy/a/projects.py
papermcpy/a/utils.py
papermcpy/a/versions.py
papermcpy-0.0.4.dist-info/LICENSE.md
papermcpy-0.0.4.dist-info/METADATA
papermcpy-0.0.4.dist-info/WHEEL
papermcpy-0.0.4.dist-info/top_level.txt
papermcpy-0.0.4.dist-info/RECORD
