Metadata-Version: 2.1
Name: papermcpy
Version: 0.0.4
Summary: PaperMC API Wrapper
Home-page: https://github.com/nevalicjus/papermcpy
Author: Nevalicjus
Author-email: nevalicjus@gmail.com
License: UNKNOWN
Project-URL: Author, https://n3v.xyz
Project-URL: Bug Tracker, https://github.com/nevalicjus/papermcpy/issues
Platform: UNKNOWN
Classifier: Programming Language :: Python :: 3
Classifier: License :: OSI Approved :: MIT License
Classifier: Operating System :: OS Independent
Requires-Python: >=3.6
License-File: LICENSE.md
Requires-Dist: requests
